wispyjim/__init__.py
wispyjim/classes.py
wispyjim/main.py
wispyjim-1.3.8.dist-info/LICENSE.md
wispyjim-1.3.8.dist-info/METADATA
wispyjim-1.3.8.dist-info/WHEEL
wispyjim-1.3.8.dist-info/top_level.txt
wispyjim-1.3.8.dist-info/RECORD
